gzip_utils/__init__.py
gzip_utils/_compressed_json_list.py
gzip_utils/_exceptions.py
gzip_utils/py.typed
gzip_utils-2020.7.15.dist-info/entry_points.txt
gzip_utils-2020.7.15.dist-info/LICENSE
gzip_utils-2020.7.15.dist-info/WHEEL
gzip_utils-2020.7.15.dist-info/METADATA
gzip_utils-2020.7.15.dist-info/RECORD
